LICENSE
MANIFEST.in
README
setup.py
django_djikiki.egg-info/PKG-INFO
django_djikiki.egg-info/SOURCES.txt
django_djikiki.egg-info/dependency_links.txt
django_djikiki.egg-info/not-zip-safe
django_djikiki.egg-info/top_level.txt
djikiki/__init__.py
djikiki/admin.py
djikiki/adminviews.py
djikiki/decorators.py
djikiki/djikikisettings.py
djikiki/forms.py
djikiki/models.py
djikiki/setup.py
djikiki/tests.py
djikiki/urls.py
djikiki/userforms.py
djikiki/userviews.py
djikiki/views.py
djikiki/creole/__init__.py
djikiki/creole/creole.py
djikiki/creole/creole2html.py
djikiki/templates/djikiki/base.html
djikiki/templates/djikiki/category.html
djikiki/templates/djikiki/create.html
djikiki/templates/djikiki/detail.html
djikiki/templates/djikiki/discuss.html
djikiki/templates/djikiki/edit.html
djikiki/templates/djikiki/featured.html
djikiki/templates/djikiki/index.html
djikiki/templates/djikiki/oldpage.html
djikiki/templates/djikiki/paginate.html
djikiki/templates/djikiki/revisions.html
djikiki/templates/djikiki/useredits.html
djikiki/templates/djikiki/userlist.html
project/__init__.py
project/manage.py
project/settings.py
project/urls.py
project/userforms.py
project/djikiki/__init__.py
project/djikiki/admin.py
project/djikiki/adminviews.py
project/djikiki/decorators.py
project/djikiki/djikikisettings.py
project/djikiki/forms.py
project/djikiki/models.py
project/djikiki/setup.py
project/djikiki/tests.py
project/djikiki/urls.py
project/djikiki/userforms.py
project/djikiki/userviews.py
project/djikiki/views.py
project/djikiki/creole/__init__.py
project/djikiki/creole/creole.py
project/djikiki/creole/creole2html.py